zoomcam/__init__.py
zoomcam/cli.py
zoomcam/config/__init__.py
zoomcam/config/config_manager.py
zoomcam/config/defaults.py
zoomcam/config/validator.py
zoomcam/core/__init__.py
zoomcam/core/auto_config_manager.py
zoomcam/core/camera_manager.py
zoomcam/core/css_layout_manager.py
zoomcam/core/git_logger.py
zoomcam/core/interpolation_engine.py
zoomcam/core/layout_engine.py
zoomcam/core/motion_detector.py
zoomcam/core/recorder.py
zoomcam/core/stream_processor.py
zoomcam/main.py
zoomcam/utils/__init__.py
zoomcam/utils/exceptions.py
zoomcam/utils/helpers.py
zoomcam/utils/logger.py
zoomcam/utils/performance.py
zoomcam/web/__init__.py
zoomcam/web/api.py
zoomcam/web/auth.py
zoomcam/web/events.py
zoomcam/web/static/css/admin-panel.css
zoomcam/web/static/css/dynamic-layouts.css
zoomcam/web/static/css/style.css
zoomcam/web/static/css/timeline.css
zoomcam/web/static/images/favicon.ico
zoomcam/web/static/images/icons/camera.svg
zoomcam/web/static/images/icons/motion.svg
zoomcam/web/static/images/icons/settings.svg
zoomcam/web/static/images/logo.png
zoomcam/web/static/js/config-visualizer.js
zoomcam/web/static/js/config.js
zoomcam/web/static/js/layout-adapter.js
zoomcam/web/static/js/player.js
zoomcam/web/static/js/real-time-monitor.js
zoomcam/web/static/js/setup-wizard.js
zoomcam/web/static/js/timeline.js
zoomcam/web/templates/admin-monitor.html
zoomcam/web/templates/base.html
zoomcam/web/templates/config.html
zoomcam/web/templates/index.html
zoomcam/web/templates/layout-preview.html
zoomcam/web/templates/timeline.html
zoomcam-0.1.2.dist-info/LICENSE
zoomcam-0.1.2.dist-info/METADATA
zoomcam-0.1.2.dist-info/WHEEL
zoomcam-0.1.2.dist-info/entry_points.txt
zoomcam-0.1.2.dist-info/RECORD
